{
    "key": "group_689db7f0a73f5",
    "title": "CPT: Лікарі",
    "fields": [
        {
            "key": "field_689db87f92d6f",
            "label": "Стаж",
            "name": "experience",
            "aria-label": "",
            "type": "number",
            "instructions": "",
            "required": 0,
            "conditional_logic": 0,
            "wrapper": {
                "width": "",
                "class": "",
                "id": ""
            },
            "default_value": "",
            "min": "",
            "max": "",
            "allow_in_bindings": 0,
            "placeholder": "",
            "step": "",
            "prepend": "",
            "append": ""
        },
        {
            "key": "field_689db7f092d6e",
            "label": "Запис відкритий",
            "name": "sign_up_open",
            "aria-label": "",
            "type": "true_false",
            "instructions": "",
            "required": 0,
            "conditional_logic": 0,
            "wrapper": {
                "width": "",
                "class": "",
                "id": ""
            },
            "message": "",
            "default_value": 0,
            "allow_in_bindings": 0,
            "ui_on_text": "",
            "ui_off_text": "",
            "ui": 1
        },
        {
            "key": "field_689dc462ffcb0",
            "label": "Ціна консультації",
            "name": "consultation_price",
            "aria-label": "",
            "type": "number",
            "instructions": "",
            "required": 0,
            "conditional_logic": 0,
            "wrapper": {
                "width": "",
                "class": "",
                "id": ""
            },
            "default_value": "",
            "min": "",
            "max": "",
            "allow_in_bindings": 0,
            "placeholder": "",
            "step": "",
            "prepend": "",
            "append": ""
        },
        {
            "key": "field_68c95db7ce157",
            "label": "Інформація",
            "name": "information",
            "aria-label": "",
            "type": "repeater",
            "instructions": "",
            "required": 0,
            "conditional_logic": 0,
            "wrapper": {
                "width": "",
                "class": "",
                "id": ""
            },
            "layout": "table",
            "pagination": 0,
            "min": 0,
            "max": 0,
            "collapsed": "",
            "button_label": "Додати рядок",
            "rows_per_page": 20,
            "sub_fields": [
                {
                    "key": "field_68c95dccce158",
                    "label": "Заголовок",
                    "name": "title",
                    "aria-label": "",
                    "type": "text",
                    "instructions": "",
                    "required": 0,
                    "conditional_logic": 0,
                    "wrapper": {
                        "width": "",
                        "class": "",
                        "id": ""
                    },
                    "default_value": "",
                    "maxlength": "",
                    "allow_in_bindings": 0,
                    "placeholder": "",
                    "prepend": "",
                    "append": "",
                    "parent_repeater": "field_68c95db7ce157"
                },
                {
                    "key": "field_68c95dd4ce159",
                    "label": "Контент",
                    "name": "content",
                    "aria-label": "",
                    "type": "wysiwyg",
                    "instructions": "",
                    "required": 0,
                    "conditional_logic": 0,
                    "wrapper": {
                        "width": "",
                        "class": "",
                        "id": ""
                    },
                    "default_value": "",
                    "allow_in_bindings": 0,
                    "tabs": "all",
                    "toolbar": "full",
                    "media_upload": 1,
                    "delay": 0,
                    "parent_repeater": "field_68c95db7ce157"
                }
            ]
        }
    ],
    "location": [
        [
            {
                "param": "post_type",
                "operator": "==",
                "value": "doctors"
            }
        ]
    ],
    "menu_order": 0,
    "position": "normal",
    "style": "default",
    "label_placement": "top",
    "instruction_placement": "label",
    "hide_on_screen": [
        "the_content"
    ],
    "active": true,
    "description": "",
    "show_in_rest": 0,
    "modified": 1760618894
}
